ensemble/_RESSEL.py
ensemble/__init__.py
utils/__init__.py
utils/_split.py
utils/_transformer.py
InstanceSelectionDNX-3.3.dist-info/LICENSE
InstanceSelectionDNX-3.3.dist-info/METADATA
InstanceSelectionDNX-3.3.dist-info/WHEEL
InstanceSelectionDNX-3.3.dist-info/top_level.txt
InstanceSelectionDNX-3.3.dist-info/RECORD
