Metadata-Version: 2.1
Name: InstanceSelectionDNX
Version: 3.3
Summary: Instance Selection Algorithms.
Home-page: https://github.com/dpr1005/Semisupervised-learning-and-instance-selection-methods
Download-URL: https://github.com/dpr1005/Semisupervised-learning-and-instance-selection-methods
Author: Daniel Puente Ramírez
Author-email: dani.pr21@gmail.com
License: MIT
Project-URL: Bug Tracker, https://github.com/dpr1005/Semisupervised-learning-and-instance-selection-methods/issues
Keywords: Instance Selection,ML,IA
Classifier: Programming Language :: Python :: 3
Classifier: License :: OSI Approved :: MIT License
Classifier: Operating System :: OS Independent
Classifier: Development Status :: 4 - Beta
Requires-Python: >=3.7
License-File: LICENSE
